FL/FLdict.py
FL/__init__.py
FL/_version.py
FL/cmdline.py
FL/constants.py
FL/fl_cmd.py
FL/py.typed
FL/fake/Base.py
FL/fake/Font.py
FL/fake/FontImporter.py
FL/fake/Kerning.py
FL/fake/KerningClass.py
FL/fake/__init__.py
FL/fake/mixins.py
FL/helpers/FLList.py
FL/helpers/ListParent.py
FL/helpers/__init__.py
FL/helpers/classList.py
FL/helpers/math.py
FL/helpers/nametables.py
FL/helpers/registry.py
FL/helpers/tth.py
FL/objects/Anchor.py
FL/objects/AuditRecord.py
FL/objects/Canvas.py
FL/objects/Component.py
FL/objects/Dialog.py
FL/objects/Encoding.py
FL/objects/EncodingRecord.py
FL/objects/Feature.py
FL/objects/Font.py
FL/objects/FontLab.py
FL/objects/Glyph.py
FL/objects/Guide.py
FL/objects/Hint.py
FL/objects/Image.py
FL/objects/KerningPair.py
FL/objects/Link.py
FL/objects/Matrix.py
FL/objects/NameRecord.py
FL/objects/Node.py
FL/objects/Options.py
FL/objects/Point.py
FL/objects/Rect.py
FL/objects/Replace.py
FL/objects/TTGasp.py
FL/objects/TTH.py
FL/objects/TTHCommand.py
FL/objects/TTHPoint.py
FL/objects/TTHProblem.py
FL/objects/TTInfo.py
FL/objects/TTPoint.py
FL/objects/TTStem.py
FL/objects/TTVdmx.py
FL/objects/TrueTypeTable.py
FL/objects/Uni.py
FL/objects/WeightVector.py
FL/objects/__init__.py
FL/vfb/__init__.py
FL/vfb/reader.py
FL/vfb/writer.py
fakelab-0.1.2.dist-info/METADATA
fakelab-0.1.2.dist-info/WHEEL
fakelab-0.1.2.dist-info/entry_points.txt
fakelab-0.1.2.dist-info/top_level.txt
fakelab-0.1.2.dist-info/RECORD
