Metadata-Version: 2.4
Name: fakelab
Version: 0.1.2
Summary: Fake FontLab Studio 5 for automated tests and external scripting
Author-email: Jens Kutílek <webmail@kutilek.de>
License-Expression: GPL-3.0-or-later
Project-URL: Homepage, https://github.com/jenskutilek/fakelab
Project-URL: Documentation, https://fakelab.readthedocs.io/
Project-URL: Bug Tracker, https://github.com/jenskutilek/fakelab/issues
Project-URL: Changelog, https://github.com/jenskutilek/fakelab/blob/main/CHANGELOG.md
Keywords: vfb,fonttools
Classifier: Environment :: Console
Classifier: Operating System :: OS Independent
Classifier: Programming Language :: Python
Classifier: Programming Language :: Python :: 3 :: Only
Classifier: Programming Language :: Python :: 3.10
Classifier: Programming Language :: Python :: 3.11
Classifier: Programming Language :: Python :: 3.12
Classifier: Programming Language :: Python :: 3.13
Requires-Python: >=3.10
Provides-Extra: all
Requires-Dist: fakelab[generate]; extra == "all"
Requires-Dist: fakelab[repl]; extra == "all"
Requires-Dist: fakelab[vfb]; extra == "all"
Provides-Extra: generate
Requires-Dist: ufo2ft>=3.6.2; extra == "generate"
Requires-Dist: fakelab[vfb]; extra == "generate"
Provides-Extra: repl
Requires-Dist: ptpython>=3.0.30; extra == "repl"
Provides-Extra: vfb
Requires-Dist: vfbLib>=0.10.4; extra == "vfb"
Provides-Extra: test
Requires-Dist: mypy; extra == "test"
Requires-Dist: pytest; extra == "test"
Requires-Dist: pytest-black-ng; extra == "test"
Requires-Dist: pytest-cov; extra == "test"
Requires-Dist: pytest-isort; extra == "test"
Requires-Dist: pytest-mock; extra == "test"
Requires-Dist: pytest-mypy; extra == "test"
Requires-Dist: pytest-pylint; extra == "test"
Requires-Dist: ruff; extra == "test"
Provides-Extra: dev
Requires-Dist: build; extra == "dev"
Requires-Dist: flake8; extra == "dev"
Requires-Dist: wheel; extra == "dev"
Requires-Dist: ruff; extra == "dev"
Requires-Dist: setuptools-scm[toml]; extra == "dev"
Provides-Extra: doc
Requires-Dist: sphinx>=8.2.3; extra == "doc"
Requires-Dist: sphinx_rtd_theme; extra == "doc"
